sqlatracker/__init__.py
sqlatracker/field_tracker.py
sqlatracker/utils.py
sqlatracker-0.0.7.dist-info/LICENSE
sqlatracker-0.0.7.dist-info/WHEEL
sqlatracker-0.0.7.dist-info/METADATA
sqlatracker-0.0.7.dist-info/RECORD
